<?xml version="1.0" standalone="yes"?>
<RECORDS>

    <RECORD>
        <id>175</id>
        <name>杭州市</name>
        <parent_id>11</parent_id>
        <levels>2</levels>
        <longitude></longitude>
        <latitude></latitude>
    </RECORD>
    <RECORD>
        <id>176</id>
        <name>宁波市</name>
        <parent_id>11</parent_id>
        <levels>2</levels>
        <longitude></longitude>
        <latitude></latitude>
    </RECORD>
    <RECORD>
        <id>177</id>
        <name>温州市</name>
        <parent_id>11</parent_id>
        <levels>2</levels>
        <longitude></longitude>
        <latitude></latitude>
    </RECORD>
    <RECORD>
        <id>178</id>
        <name>嘉兴市</name>
        <parent_id>11</parent_id>
        <levels>2</levels>
        <longitude></longitude>
        <latitude></latitude>
    </RECORD>
    <RECORD>
        <id>179</id>
        <name>湖州市</name>
        <parent_id>11</parent_id>
        <levels>2</levels>
        <longitude></longitude>
        <latitude></latitude>
    </RECORD>
    <RECORD>
        <id>180</id>
        <name>绍兴市</name>
        <parent_id>11</parent_id>
        <levels>2</levels>
        <longitude></longitude>
        <latitude></latitude>
    </RECORD>
    <RECORD>
        <id>181</id>
        <name>舟山市</name>
        <parent_id>11</parent_id>
        <levels>2</levels>
        <longitude></longitude>
        <latitude></latitude>
    </RECORD>
    <RECORD>
        <id>182</id>
        <name>衢州市</name>
        <parent_id>11</parent_id>
        <levels>2</levels>
        <longitude></longitude>
        <latitude></latitude>
    </RECORD>
    <RECORD>
        <id>183</id>
        <name>金华市</name>
        <parent_id>11</parent_id>
        <levels>2</levels>
        <longitude></longitude>
        <latitude></latitude>
    </RECORD>
    <RECORD>
        <id>184</id>
        <name>台州市</name>
        <parent_id>11</parent_id>
        <levels>2</levels>
        <longitude></longitude>
        <latitude></latitude>
    </RECORD>
    <RECORD>
        <id>185</id>
        <name>丽水市</name>
        <parent_id>11</parent_id>
        <levels>2</levels>
        <longitude></longitude>
        <latitude></latitude>
    </RECORD>
</RECORDS>